pymindhome/__init__.py
pymindhome/api.py
pymindhome/errors.py
pymindhome/events.py
pymindhome-0.1.1.dist-info/WHEEL
pymindhome-0.1.1.dist-info/METADATA
pymindhome-0.1.1.dist-info/RECORD
