Metadata-Version: 2.1
Name: pymindhome
Version: 0.1.1
Summary: A Python3, asyncio library for interacting with the MindHome REST API
Author: Aaron Bach
Author-email: aaron@mysmartinsure.com
Requires-Python: >=3.6.0,<4.0.0
Classifier: Programming Language :: Python :: 3
Classifier: Programming Language :: Python :: 3.6
Classifier: Programming Language :: Python :: 3.7
Classifier: Programming Language :: Python :: 3.8
Requires-Dist: aiohttp (>=3.6.2,<4.0.0)
Requires-Dist: pylint (>=2.5.3,<3.0.0)
